shekar/__init__.py
shekar/base.py
shekar/hub.py
shekar/normalizer.py
shekar/pipeline.py
shekar/utils.py
shekar/data/__init__.py
shekar/data/readme.md
shekar/data/files/__init__.py
shekar/data/files/compound_words.csv
shekar/data/files/informal_words.csv
shekar/data/files/offensive_words.csv
shekar/data/files/stopwords.csv
shekar/data/files/verbs.csv
shekar/data/files/vocab.csv
shekar/data/fonts/parastoo.ttf
shekar/data/fonts/sahel.ttf
shekar/data/masks/__init__.py
shekar/data/masks/bulb.png
shekar/data/masks/cat.png
shekar/data/masks/cloud.png
shekar/data/masks/head.png
shekar/data/masks/heart.png
shekar/data/masks/iran.png
shekar/embeddings/__init__.py
shekar/embeddings/albert_embedder.py
shekar/embeddings/base.py
shekar/embeddings/contextual_embedder.py
shekar/embeddings/word_embedder.py
shekar/keyword_extraction/__init__.py
shekar/keyword_extraction/base.py
shekar/keyword_extraction/rake.py
shekar/morphology/__init__.py
shekar/morphology/conjugator.py
shekar/morphology/inflector.py
shekar/morphology/lemmatizer.py
shekar/morphology/stemmer.py
shekar/ner/__init__.py
shekar/ner/albert_ner.py
shekar/ner/base.py
shekar/pos/__init__.py
shekar/pos/albert_pos.py
shekar/pos/base.py
shekar/preprocessing/__init__.py
shekar/preprocessing/maskers/__init__.py
shekar/preprocessing/maskers/diacritic_masker.py
shekar/preprocessing/maskers/digit_masker.py
shekar/preprocessing/maskers/email_masker.py
shekar/preprocessing/maskers/emoji_masker.py
shekar/preprocessing/maskers/hashtag_masker.py
shekar/preprocessing/maskers/html_tag_masker.py
shekar/preprocessing/maskers/mention_masker.py
shekar/preprocessing/maskers/non_persian_letter_masker.py
shekar/preprocessing/maskers/offensive_word_masker.py
shekar/preprocessing/maskers/punctuation_masker.py
shekar/preprocessing/maskers/stopword_masker.py
shekar/preprocessing/maskers/url_masker.py
shekar/preprocessing/normalizers/__init__.py
shekar/preprocessing/normalizers/alphabet_normalizer.py
shekar-1.3.1.dist-info/METADATA
shekar-1.3.1.dist-info/WHEEL
shekar-1.3.1.dist-info/entry_points.txt
shekar-1.3.1.dist-info/licenses/LICENSE
shekar-1.3.1.dist-info/RECORD
