Metadata-Version: 2.4
Name: shekar
Version: 1.3.1
Summary: Simplifying Persian NLP for Modern Applications
Project-URL: Homepage, https://github.com/amirivojdan/shekar
Project-URL: Repository, https://github.com/amirivojdan/shekar
Project-URL: Documentation, https://lib.shekar.io
Project-URL: Issues, https://github.com/amirivojdan/shekar/issues
Project-URL: Changelog, https://github.com/amirivojdan/shekar/releases
Author-email: Ahmad Amirivojdan <amirivojdan@gmail.com>
License-Expression: MIT
License-File: LICENSE
Keywords: Deep Learning,Machine Learning,NLP,Natural Language Processing,Persian,Shekar,Text Processing
Classifier: Development Status :: 5 - Production/Stable
Classifier: Intended Audience :: Developers
Classifier: Intended Audience :: Science/Research
Classifier: License :: OSI Approved :: MIT License
Classifier: Natural Language :: Persian
Classifier: Operating System :: OS Independent
Classifier: Programming Language :: Python
Classifier: Programming Language :: Python :: 3
Classifier: Programming Language :: Python :: 3 :: Only
Classifier: Programming Language :: Python :: 3.10
Classifier: Programming Language :: Python :: 3.11
Classifier: Programming Language :: Python :: 3.12
Classifier: Programming Language :: Python :: 3.13
Classifier: Topic :: Scientific/Engineering :: Artificial Intelligence
Classifier: Topic :: Text Processing
Classifier: Topic :: Text Processing :: Linguistic
Requires-Python: >=3.10
Requires-Dist: flashtext>=2.7
Requires-Dist: numpy>=1.24.4
Requires-Dist: onnxruntime>=1.23.2
Requires-Dist: tokenizers>=0.21.2
Requires-Dist: tqdm>=4.67.1
Provides-Extra: all
Requires-Dist: arabic-reshaper>=3.0.0; extra == 'all'
Requires-Dist: pillow>=11.2.1; extra == 'all'
Requires-Dist: python-bidi>=0.6.6; extra == 'all'
Requires-Dist: wordcloud>=1.9.4; extra == 'all'
Provides-Extra: viz
Requires-Dist: arabic-reshaper>=3.0.0; extra == 'viz'
Requires-Dist: pillow>=11.2.1; extra == 'viz'
Requires-Dist: python-bidi>=0.6.6; extra == 'viz'
Requires-Dist: wordcloud>=1.9.4; extra == 'viz'
